pyqtgraph/PlotData.py
pyqtgraph/Point.py
pyqtgraph/Qt.py
pyqtgraph/SRTTransform.py
pyqtgraph/SRTTransform3D.py
pyqtgraph/SignalProxy.py
pyqtgraph/ThreadsafeTimer.py
pyqtgraph/Transform3D.py
pyqtgraph/Vector.py
pyqtgraph/WidgetGroup.py
pyqtgraph/__init__.py
pyqtgraph/colormap.py
pyqtgraph/configfile.py
pyqtgraph/debug.py
pyqtgraph/exceptionHandling.py
pyqtgraph/frozenSupport.py
pyqtgraph/functions.py
pyqtgraph/graphicsWindows.py
pyqtgraph/ordereddict.py
pyqtgraph/pgcollections.py
pyqtgraph/ptime.py
pyqtgraph/python2_3.py
pyqtgraph/reload.py
pyqtgraph/units.py
pyqtgraph/GraphicsScene/GraphicsScene.py
pyqtgraph/GraphicsScene/__init__.py
pyqtgraph/GraphicsScene/exportDialog.py
pyqtgraph/GraphicsScene/exportDialogTemplate_pyqt.py
pyqtgraph/GraphicsScene/exportDialogTemplate_pyqt5.py
pyqtgraph/GraphicsScene/exportDialogTemplate_pyside.py
pyqtgraph/GraphicsScene/exportDialogTemplate_pyside2.py
pyqtgraph/GraphicsScene/mouseEvents.py
pyqtgraph/canvas/Canvas.py
pyqtgraph/canvas/CanvasItem.py
pyqtgraph/canvas/CanvasManager.py
pyqtgraph/canvas/CanvasTemplate_pyqt.py
pyqtgraph/canvas/CanvasTemplate_pyqt5.py
pyqtgraph/canvas/CanvasTemplate_pyside.py
pyqtgraph/canvas/CanvasTemplate_pyside2.py
pyqtgraph/canvas/TransformGuiTemplate_pyqt.py
pyqtgraph/canvas/TransformGuiTemplate_pyqt5.py
pyqtgraph/canvas/TransformGuiTemplate_pyside.py
pyqtgraph/canvas/TransformGuiTemplate_pyside2.py
pyqtgraph/canvas/__init__.py
pyqtgraph/console/CmdInput.py
pyqtgraph/console/Console.py
pyqtgraph/console/__init__.py
pyqtgraph/console/template_pyqt.py
pyqtgraph/console/template_pyqt5.py
pyqtgraph/console/template_pyside.py
pyqtgraph/console/template_pyside2.py
pyqtgraph/dockarea/Container.py
pyqtgraph/dockarea/Dock.py
pyqtgraph/dockarea/DockArea.py
pyqtgraph/dockarea/DockDrop.py
pyqtgraph/dockarea/__init__.py
pyqtgraph/examples/Arrow.py
pyqtgraph/examples/BarGraphItem.py
pyqtgraph/examples/CLIexample.py
pyqtgraph/examples/ColorButton.py
pyqtgraph/examples/ConsoleWidget.py
pyqtgraph_qo-0.10.0.7.dist-info/LICENSE.txt
pyqtgraph_qo-0.10.0.7.dist-info/METADATA
pyqtgraph_qo-0.10.0.7.dist-info/WHEEL
pyqtgraph_qo-0.10.0.7.dist-info/top_level.txt
pyqtgraph_qo-0.10.0.7.dist-info/RECORD
