Metadata-Version: 2.1
Name: pyqtgraph-qo
Version: 0.10.0.7
Summary: Scientific Graphics and GUI Library for Python (QO internal use version)
Home-page: http://www.pyqtgraph.org
Author: Luke Campagnola
Author-email: luke.campagnola@gmail.com
License: MIT
Platform: UNKNOWN
Classifier: Programming Language :: Python
Classifier: Programming Language :: Python :: 2
Classifier: Programming Language :: Python :: 2.7
Classifier: Programming Language :: Python :: 3
Classifier: Development Status :: 4 - Beta
Classifier: Environment :: Other Environment
Classifier: Intended Audience :: Science/Research
Classifier: License :: OSI Approved :: MIT License
Classifier: Operating System :: OS Independent
Classifier: Topic :: Software Development :: Libraries :: Python Modules
Classifier: Topic :: Scientific/Engineering :: Visualization
Classifier: Topic :: Software Development :: User Interfaces
Requires-Dist: numpy (>=1.8.0)
